adafruit_mcp4728.py
adafruit_circuitpython_mcp4728-1.3.14.dist-info/licenses/LICENSE
adafruit_circuitpython_mcp4728-1.3.14.dist-info/METADATA
adafruit_circuitpython_mcp4728-1.3.14.dist-info/WHEEL
adafruit_circuitpython_mcp4728-1.3.14.dist-info/top_level.txt
adafruit_circuitpython_mcp4728-1.3.14.dist-info/RECORD
