Metadata-Version: 2.4
Name: adafruit-circuitpython-mcp4728
Version: 1.3.14
Summary: Helper library for the MCP4728 I2C 12-bit Quad DAC
Author-email: Adafruit Industries <circuitpython@adafruit.com>
License: MIT
Project-URL: Homepage, https://github.com/adafruit/Adafruit_CircuitPython_MCP4728
Keywords: adafruit,blinka,circuitpython,micropython,mcp4728,dac,12-bit,quad,i2c
Classifier: Intended Audience :: Developers
Classifier: Topic :: Software Development :: Libraries
Classifier: Topic :: Software Development :: Embedded Systems
Classifier: Topic :: System :: Hardware
Classifier: License :: OSI Approved :: MIT License
Classifier: Programming Language :: Python :: 3
License-File: LICENSE
Requires-Dist: Adafruit-Blinka
Requires-Dist: adafruit-circuitpython-busdevice
Requires-Dist: typing-extensions~=4.0
Provides-Extra: optional
Dynamic: license-file
